csplice/__init__.py
csplice/core/__init__.py
csplice/core/gtftobed.py
csplice/core/readoverlap.py
csplice/script/__init__.py
csplice/script/cli.py
csplice-0.2.0.dist-info/METADATA
csplice-0.2.0.dist-info/WHEEL
csplice-0.2.0.dist-info/entry_points.txt
csplice-0.2.0.dist-info/RECORD
