Metadata-Version: 2.3
Name: csplice
Version: 0.2.0
Summary: Genomic data processing toolkit
License: MIT
Author: Zan Yuan
Author-email: yfinddream@gmail.com
Requires-Python: >=3.8,<4.0
Classifier: License :: OSI Approved :: MIT License
Classifier: Programming Language :: Python :: 3
Classifier: Programming Language :: Python :: 3.8
Classifier: Programming Language :: Python :: 3.9
Classifier: Programming Language :: Python :: 3.10
Classifier: Programming Language :: Python :: 3.11
Classifier: Programming Language :: Python :: 3.12
Classifier: Programming Language :: Python :: 3.13
Requires-Dist: bioframe (>=0.8.0,<0.9.0)
Requires-Dist: click (>=8.0.0,<9.0.0)
Requires-Dist: pandas (>=2.0.0,<3.0.0)
Requires-Dist: pysam (>=0.23.0,<0.24.0)
